pbn_simulation.py
plastic_balanced_network/__init__.py
plastic_balanced_network/helpers.py
plastic_balanced_network/network.py
plastic_balanced_network-0.0.6.dist-info/licenses/LICENSE.txt
plastic_balanced_network-0.0.6.dist-info/METADATA
plastic_balanced_network-0.0.6.dist-info/WHEEL
plastic_balanced_network-0.0.6.dist-info/top_level.txt
plastic_balanced_network-0.0.6.dist-info/RECORD
